[
    {
        "id": "0",
        "title": "Top",
        "num": 1,
        "datas": {
            "id":"2",
            "serieses":
            [
                {
                    "id": "0",
                    "title": "小説シリーズ１",
                    "num": 1,
                    "datas":
                    {
                        "id":"3",
                        "serieses":[],
                        "details":[]
                    }
                },
                {
                    "id": "1",
                    "title": "作者名",
                    "num": 2,
                    "datas":
                    {
                        "id": "5",
                        "serieses":[
                            {
                                "id": "0",
                                "title": "小説２",
                                "num": 2,
                                "datas":
                                {
                                    "id":"3",
                                    "serieses":[],
                                    "details":[]
                                }
                            }
                        ],
                        "details":[
                            {
                                "id": "3",
                                "title": "△□作家",
                                "message": "〇〇大賞受賞"
                            },
                        ]
                    }
                }
            ],
            "details": [
                {
                    "id": "0",
                    "title": "概要",
                    "message": "いろいろなシリーズを追加していく"
                }
            ]
        }
    }
]
